analytics_toolbox/__init__.py
analytics_toolbox/_nbdev.py
analytics_toolbox/connector.py
analytics_toolbox/core.py
analytics_toolbox/data.py
analytics_toolbox/db.py
analytics_toolbox/helpers.py
analytics_toolbox/logtools.py
analytics_toolbox/s3funcs.py
analytics_toolbox/slackfuncs.py
analytics_toolbox-0.1.1.dist-info/LICENSE
analytics_toolbox-0.1.1.dist-info/METADATA
analytics_toolbox-0.1.1.dist-info/WHEEL
analytics_toolbox-0.1.1.dist-info/entry_points.txt
analytics_toolbox-0.1.1.dist-info/top_level.txt
analytics_toolbox-0.1.1.dist-info/RECORD
