Metadata-Version: 2.1
Name: analytics-toolbox
Version: 0.1.1
Summary: A toolbox for Analytics and Research.
Home-page: https://github.com/htpeter/analytics_toolbox
Author: github.com/htpeter
Author-email: peter@kouvaris.io
License: Apache Software License 2.0
Keywords: data,analytics,science,research,database
Platform: UNKNOWN
Classifier: Development Status :: 3 - Alpha
Classifier: Intended Audience :: Developers
Classifier: License :: OSI Approved :: Apache Software License
Classifier: Natural Language :: English
Classifier: Programming Language :: Python :: 3.6
Classifier: Programming Language :: Python :: 3.7
Classifier: Programming Language :: Python :: 3.8
Requires-Python: >=3.6
